{"configuration": {"entity_configs": [], "iw_mappings": [{"recommendation": {"table_group_name": "ORDER_DETAILS_TG", "source_name": "DEMO_ORACLE"}, "entity_id": "e8c11acef2f776346e25504e", "entity_type": "table_group"}, {"recommendation": {"table_group_name": "PRODUCTS_TG", "source_name": "DEMO_CSV"}, "entity_id": "b2123594bec8d642f0203046", "entity_type": "table_group"}, {"recommendation": {"pipeline_name": "DEMO_PIPELINE", "domain_name": "DEMO_DOMAIN"}, "entity_id": "83c15fb2157347a1e4ff030b", "entity_type": "pipeline"}], "entity": {"entity_name": "DEMO_WORKFLOW", "entity_id": "77f68f74d3ec09a4cff076f2", "entity_type": "workflow"}, "workflow": {"description": "", "workflow_graph": {"tasks": [{"is_group": false, "title": "Ingest DEMO_ORACLE", "description": "", "task_id": "SI_MNPE", "task_type": "ingest_table_group", "location": "-365 -95", "run_properties": {"num_retries": 0, "trigger_rule": "all_success"}, "task_properties": {"source_id": "1d6fae5b9c1d6359d4f0cf1e", "table_group_id": "e8c11acef2f776346e25504e", "ingest_type": "all"}}, {"is_group": false, "title": "Ingest DEMO_CSV", "description": "", "task_id": "SI_20BF", "task_type": "ingest_table_group", "location": "-365 25", "run_properties": {"num_retries": 0, "trigger_rule": "all_success"}, "task_properties": {"source_id": "dd8b62c3b9455d0b4b016c4d", "table_group_id": "b2123594bec8d642f0203046", "ingest_type": "all"}}, {"is_group": false, "title": "Build DEMO_PIPELINE", "description": "", "task_id": "PB_2MXY", "task_type": "pipeline_build", "location": "-205 -35", "run_properties": {"num_retries": 0, "trigger_rule": "all_success"}, "task_properties": {"pipeline_id": "83c15fb2157347a1e4ff030b", "version_id": "a9407d6a7caee5261d84dc93", "version": 1, "pipeline_parameters": []}}, {"is_group": false, "title": "Bash Script", "description": "", "task_id": "BS_7IEV", "task_type": "bash_command_run", "location": "-45 -35", "run_properties": {"num_retries": 0, "trigger_rule": "all_success"}, "task_properties": {"bash_command": "echo \"Completed job successfully!\""}}], "edges": [{"from_task": "SI_MNPE", "to_task": "PB_2MXY", "category": "LINK"}, {"from_task": "SI_20BF", "to_task": "PB_2MXY", "category": "LINK"}, {"from_task": "PB_2MXY", "to_task": "BS_7IEV", "category": "LINK"}]}}, "export": {"exported_at": "2022-06-16T09:16:51.698Z", "exported_by": "Infoworks Admin"}}, "environment_configurations": {"environment_name": ["PRE_PROD_NOVARTIS"], "environment_compute_template_name": null, "environment_storage_name": null}, "user_email": "admin@infoworks.io"}